equasolverpro/__init__.py
equasolverpro/components.py
equasolverpro/linear.py
equasolverpro/quadratic.py
EquaSolverPro-0.0.1.dist-info/METADATA
EquaSolverPro-0.0.1.dist-info/WHEEL
EquaSolverPro-0.0.1.dist-info/top_level.txt
EquaSolverPro-0.0.1.dist-info/RECORD
