Metadata-Version: 2.1
Name: EquaSolverPro
Version: 0.0.1
Summary: Python Function to solve linear and quadratic equations
Author: Snehashish Laskar
Classifier: Programming Language :: Python :: 3
Classifier: License :: OSI Approved :: MIT License
Classifier: Operating System :: OS Independent
Requires-Python: >=3.8
Requires-Dist: math
